<Prefab>
  <Parameters>
    <Parameter Name="AttackerFillBarBrush" DefaultValue="PowerLevelComparer.LeftBar.Battle" />
    <Parameter Name="DefenderFillBarBrush" DefaultValue="PowerLevelComparer.RightBar.Battle" />
    <Parameter Name="CenterSpace" DefaultValue="0" />
    <Parameter Name="IsCenterSeperatorEnabled" DefaultValue="false" />
  </Parameters>
  <Window>

    <PowerLevelComparerWidget WidthSizePolicy="Fixed" HeightSizePolicy="Fixed" SuggestedWidth="400" SuggestedHeight="10" AttackerPower="@AttackerBattlePowerValue" AttackerPowerListPanel="PowerListPanel\AttackerSideInitialPowerLevel\AttackerPowerListPanel" AttackerPowerWidget="PowerListPanel\AttackerSideInitialPowerLevel" CenterSeperatorWidget="CenterSeperatorWidget" DefenderPower="@DefenderBattlePowerValue" DefenderPowerListPanel="PowerListPanel\DefenderSideInitialPowerLevel\DefenderPowerListPanel" DefenderPowerWidget="PowerListPanel\DefenderSideInitialPowerLevel" InitialAttackerBattlePower="@InitialAttackerBattlePowerValue" InitialDefenderBattlePower="@InitialDefenderBattlePowerValue" IsCenterSeperatorEnabled="*IsCenterSeperatorEnabled" PowerListPanel="PowerListPanel" >
      <Children>

        <ListPanel Id="PowerListPanel" WidthSizePolicy="StretchToParent" HeightSizePolicy="StretchToParent" LayoutImp.LayoutMethod="HorizontalLeftToRight">
          <Children>

            <Widget Id="AttackerSideInitialPowerLevel" WidthSizePolicy="StretchToParent" HeightSizePolicy="StretchToParent" Brush="*AttackerFillBarBrush" Brush.Color="#00000088">
              <Children>
                <ListPanel Id="AttackerPowerListPanel" WidthSizePolicy="StretchToParent" HeightSizePolicy="StretchToParent" LayoutImp.LayoutMethod="HorizontalLeftToRight">
                  <Children>
                    <Widget Id="AttackerSideEmptyPowerLevel" WidthSizePolicy="StretchToParent" HeightSizePolicy="StretchToParent" />
                    <Widget Id="AttackerSidePowerLevel" WidthSizePolicy="StretchToParent" HeightSizePolicy="StretchToParent" Brush="*AttackerFillBarBrush" Brush.Color="@AttackerColor" />
                  </Children>
                </ListPanel>
              </Children>
            </Widget>

            <Widget WidthSizePolicy="Fixed" HeightSizePolicy="StretchToParent" SuggestedWidth="*CenterSpace" />

            <Widget Id="DefenderSideInitialPowerLevel" WidthSizePolicy="StretchToParent" HeightSizePolicy="StretchToParent" Brush="*DefenderFillBarBrush" Brush.Color="#00000088">
              <Children>
                <ListPanel Id="DefenderPowerListPanel" WidthSizePolicy="StretchToParent" HeightSizePolicy="StretchToParent" LayoutImp.LayoutMethod="HorizontalLeftToRight">
                  <Children>
                    <Widget Id="DefenderSidePowerLevel" WidthSizePolicy="StretchToParent" HeightSizePolicy="StretchToParent" Brush="*DefenderFillBarBrush" Brush.Color="@DefenderColor" />
                    <Widget Id="DefenderSideEmptyPowerLevel" WidthSizePolicy="StretchToParent" HeightSizePolicy="StretchToParent" />
                  </Children>
                </ListPanel>
              </Children>
            </Widget>
          </Children>
        </ListPanel>

        <Widget Id="CenterSeperatorWidget" WidthSizePolicy="Fixed" HeightSizePolicy="Fixed" SuggestedWidth="10" SuggestedHeight="21" PositionYOffset="-5" Sprite="Clan\slider_white_tick" IsVisible="*IsCenterSeperatorEnabled" />
        <HintWidget DataSource="{Hint}" WidthSizePolicy="StretchToParent" HeightSizePolicy="StretchToParent" Command.HoverBegin="ExecuteBeginHint" Command.HoverEnd="ExecuteEndHint" />
      
      </Children>
    </PowerLevelComparerWidget>
  </Window>
</Prefab>
